examples/__init__.py
examples/tutorial.py
net_file/__init__.py
net_file/common.py
net_file/http_file.py
net_file/local_file.py
net_file/net_file.py
net_file/sftp_file.py
tests/__init__.py
tests/test_read_local_file.py
net_file-1.1.6.dist-info/LICENSE
net_file-1.1.6.dist-info/METADATA
net_file-1.1.6.dist-info/WHEEL
net_file-1.1.6.dist-info/top_level.txt
net_file-1.1.6.dist-info/RECORD
