Metadata-Version: 2.1
Name: net-file
Version: 1.1.6
Summary: Ranged read file access abstraction.
Home-page: https://gitlab.com/kraevs/net-file
Author: Stanislav Kraev
Author-email: stanislav.kraev@gmail.com
License: MIT
Project-URL: Code, https://gitlab.com/kraevs/net-file
Project-URL: Issue tracker, https://gitlab.com/kraevs/net-file/issues
Platform: any
Classifier: License :: OSI Approved :: MIT License
Classifier: Programming Language :: Python :: 3.6
Classifier: Programming Language :: Python :: 3.7
Classifier: Programming Language :: Python :: 3.8
Requires-Python: >=3.6
Requires-Dist: requests (==2.24.0)
Requires-Dist: paramiko (==2.7.1)
